LICENSE.txt
README.md
setup.cfg
setup.py
dejancv/ClassificationModule.py
dejancv/ColorModule.py
dejancv/FPS.py
dejancv/FaceDetectionModule.py
dejancv/FaceMeshModule.py
dejancv/HandTrackingModule.py
dejancv/PIDModule.py
dejancv/PlotModule.py
dejancv/PoseModule.py
dejancv/SelfiSegmentationModule.py
dejancv/SerialModule.py
dejancv/Utils.py
dejancv/__init__.py
dejancv.egg-info/PKG-INFO
dejancv.egg-info/SOURCES.txt
dejancv.egg-info/dependency_links.txt
dejancv.egg-info/requires.txt
dejancv.egg-info/top_level.txt