Metadata-Version: 2.1
Name: dejancv
Version: 2024.0.1
Summary: Computer Vision Library
Home-page: https://github.com/user/reponame
Download-URL: https://github.com/user/reponame/archive/v_01.tar.gz
Author: Dejan Chandra Gope
Author-email: dejan.gope23@gmail.com
License: MIT
Keywords: Computer Vision,Open CV,Detection
Classifier: Development Status :: 3 - Alpha
Classifier: Intended Audience :: Developers
Classifier: Topic :: Software Development :: Build Tools
Classifier: License :: OSI Approved :: MIT License
Classifier: Programming Language :: Python :: 3
Classifier: Programming Language :: Python :: 3.4
Classifier: Programming Language :: Python :: 3.5
Classifier: Programming Language :: Python :: 3.6
Classifier: Programming Language :: Python :: 3.7
Classifier: Programming Language :: Python :: 3.8
Classifier: Programming Language :: Python :: 3.9
Classifier: Programming Language :: Python :: 3.10
Classifier: Programming Language :: Python :: 3.11
License-File: LICENSE.txt
